{"error": false, "size": [1920, 1080], "name": "Denis in shcool", "version": "1.6", "location": {"label": {"deadw": ["game/dialogs/ChapterOne.rpy", 1], "kanon": ["game/dialogs/ChapterOne.rpy", 70], "adray": ["game/dialogs/ChapterOne.rpy", 73], "loli": ["game/dialogs/ChapterOne.rpy", 373], "kto": ["game/dialogs/ChapterOne.rpy", 387], "love": ["game/dialogs/ChapterOne.rpy", 401], "ad": ["game/dialogs/ChapterOne.rpy", 439], "maks_sasha": ["game/dialogs/ChapterOne.rpy", 736], "ray": ["game/dialogs/ChapterOne.rpy", 840], "ostatsa_v_ray": ["game/dialogs/ChapterOne.rpy", 951], "kirliskat": ["game/dialogs/ChapterOne.rpy", 965], "vashniy_vibor": ["game/dialogs/ChapterOne.rpy", 976], "cerkov": ["game/dialogs/ChapterOne.rpy", 1064], "cerkov2": ["game/dialogs/ChapterOne.rpy", 1078], "boghelp": ["game/dialogs/ChapterOne.rpy", 1129], "gg": ["game/dialogs/ChapterOne.rpy", 1166], "start_battle": ["game/dialogs/battle.rpy", 70], "les": ["game/dialogs/locations.rpy", 1], "les_chose": ["game/dialogs/locations.rpy", 12], "pola": ["game/dialogs/locations.rpy", 43], "magic4": ["game/dialogs/locations.rpy", 120], "dm": ["game/dialogs/locations.rpy", 165], "dm_\u0447\u0442\u043e_\u0434\u0435\u043b\u0430\u0442\u044c": ["game/dialogs/locations.rpy", 249], "chipi": ["game/dialogs/locations.rpy", 423], "ds": ["game/dialogs/locations.rpy", 452], "matras": ["game/dialogs/locations.rpy", 613], "sadf": ["game/dialogs/locations.rpy", 634], "kudaidti": ["game/dialogs/locations.rpy", 653], "asdghd": ["game/dialogs/locations.rpy", 657], "ostatsa_v_boris": ["game/dialogs/locations.rpy", 922], "first_magic": ["game/dialogs/locations.rpy", 946], "magic2": ["game/dialogs/locations.rpy", 1063], "magic3": ["game/dialogs/locations.rpy", 1117], "asdaghd": ["game/dialogs/locations.rpy", 1265], "most": ["game/dialogs/locations.rpy", 1639], "mostm": ["game/dialogs/locations.rpy", 1660], "round_1love": ["game/dialogs/locations.rpy", 1691], "round_2love": ["game/dialogs/locations.rpy", 1710], "round_3love": ["game/dialogs/locations.rpy", 1724], "shop": ["game/dialogs/locations.rpy", 1778], "infpivo": ["game/dialogs/locations.rpy", 2114], "shop_bar": ["game/dialogs/locations.rpy", 2127], "shop23": ["game/dialogs/locations.rpy", 2133], "raskasat": ["game/dialogs/locations.rpy", 2499], "ograbit": ["game/dialogs/locations.rpy", 2529], "daun": ["game/dialogs/locations.rpy", 3072], "pizdetDenisa": ["game/dialogs/locations.rpy", 3269], "finalbost": ["game/dialogs/locations.rpy", 3322], "dansh": ["game/dialogs/locations.rpy", 3389], "dan_chose": ["game/dialogs/locations.rpy", 3413], "start": ["game/dialogs/prolog.rpy", 1], "resetInfo": ["game/dialogs/prolog.rpy", 7], "uyti": ["game/dialogs/prolog.rpy", 63], "end_game_boris": ["game/dialogs/prolog.rpy", 133], "ostatsa": ["game/dialogs/prolog.rpy", 151], "bunker": ["game/dialogs/prolog.rpy", 231], "back": ["game/dialogs/prolog.rpy", 237], "pobeg": ["game/dialogs/prolog.rpy", 286], "kto_idet": ["game/dialogs/prolog.rpy", 308], "ku": ["game/dialogs/prolog.rpy", 385], "round1": ["game/dialogs/prolog.rpy", 425], "optional_name": ["game/dialogs/prolog.rpy", 453], "optional_name2": ["game/dialogs/prolog.rpy", 486], "round3": ["game/dialogs/prolog.rpy", 522], "skolko": ["game/dialogs/prolog.rpy", 537], "posiobam": ["game/dialogs/prolog.rpy", 650], "ku2": ["game/dialogs/prolog.rpy", 734], "mfr1": ["game/dialogs/prolog.rpy", 782], "dasd": ["game/dialogs/prolog.rpy", 822], "datem": ["game/dialogs/prolog.rpy", 836], "yearm": ["game/dialogs/prolog.rpy", 845], "hourm": ["game/dialogs/prolog.rpy", 870], "morg": ["game/dialogs/prolog.rpy", 1004], "boris": ["game/dialogs/prolog.rpy", 1162], "splashscreen": ["game/init.rpy", 176], "difficulty_menu": ["game/init.rpy", 304], "prefSpeed": ["game/init.rpy", 320], "main_menu": ["game/screens.rpy", 351], "restart": ["game/screens.rpy", 354], "hard_config": ["game/screens.rpy", 895], "norm_config": ["game/screens.rpy", 900], "easy_config": ["game/screens.rpy", 905], "battle": ["game/scripts/battle/battle.rpy", 1], "player_select": ["game/scripts/battle/battle.rpy", 62], "battling": ["game/scripts/battle/battle.rpy", 216], "end_battle": ["game/scripts/battle/battle.rpy", 230], "ostavit_borisa": ["game/scripts/battle/battle.rpy", 408], "turn_actions": ["game/scripts/battle/player_actions.rpy", 1], "player_skill": ["game/scripts/battle/player_actions.rpy", 28], "target_select": ["game/scripts/battle/player_actions.rpy", 81], "battle_music": ["game/scripts/define/assets/audio.rpy", 6], "lb_by_magic": ["game/scripts/define/battle_def.rpy", 337], "select_player": ["game/scripts/define/battle_def.rpy", 342], "load_items": ["game/scripts/define/items_def.rpy", 4], "load_monsters": ["game/scripts/define/monsters_def.rpy", 1], "skill_effects": ["game/scripts/define/skill_def.rpy", 1], "load_setup": ["game/scripts/other/setup.rpy", 6]}, "define": {"config.check_conflicting_properties": ["game/gui.rpy", 16], "gui.accent_color": ["game/gui.rpy", 29], "gui.idle_color": ["game/gui.rpy", 32], "gui.idle_small_color": ["game/gui.rpy", 36], "gui.hover_color": ["game/gui.rpy", 39], "gui.selected_color": ["game/gui.rpy", 44], "gui.insensitive_color": ["game/gui.rpy", 47], "gui.muted_color": ["game/gui.rpy", 51], "gui.hover_muted_color": ["game/gui.rpy", 52], "gui.text_color": ["game/gui.rpy", 55], "gui.interface_text_color": ["game/gui.rpy", 56], "gui.text_font": ["game/gui.rpy", 62], "gui.name_text_font": ["game/gui.rpy", 65], "gui.interface_text_font": ["game/gui.rpy", 68], "gui.text_size": ["game/gui.rpy", 71], "gui.name_text_size": ["game/gui.rpy", 74], "gui.interface_text_size": ["game/gui.rpy", 77], "gui.label_text_size": ["game/gui.rpy", 80], "gui.notify_text_size": ["game/gui.rpy", 83], "gui.title_text_size": ["game/gui.rpy", 86], "gui.main_menu_background": ["game/gui.rpy", 92], "gui.game_menu_background": ["game/gui.rpy", 93], "gui.textbox_height": ["game/gui.rpy", 101], "gui.textbox_yalign": ["game/gui.rpy", 105], "gui.name_xpos": ["game/gui.rpy", 111], "gui.name_ypos": ["game/gui.rpy", 112], "gui.name_xalign": ["game/gui.rpy", 117], "gui.namebox_width": ["game/gui.rpy", 121], "gui.namebox_height": ["game/gui.rpy", 122], "gui.namebox_borders": ["game/gui.rpy", 126], "gui.namebox_tile": ["game/gui.rpy", 130], "gui.dialogue_xpos": ["game/gui.rpy", 136], "gui.dialogue_ypos": ["game/gui.rpy", 137], "gui.dialogue_width": ["game/gui.rpy", 140], "gui.dialogue_text_xalign": ["game/gui.rpy", 145], "gui.button_width": ["game/gui.rpy", 155], "gui.button_height": ["game/gui.rpy", 156], "gui.button_borders": ["game/gui.rpy", 159], "gui.button_tile": ["game/gui.rpy", 163], "gui.button_text_font": ["game/gui.rpy", 166], "gui.button_text_size": ["game/gui.rpy", 169], "gui.button_text_idle_color": ["game/gui.rpy", 172], "gui.button_text_hover_color": ["game/gui.rpy", 173], "gui.button_text_selected_color": ["game/gui.rpy", 174], "gui.button_text_insensitive_color": ["game/gui.rpy", 175], "gui.button_text_xalign": ["game/gui.rpy", 179], "gui.radio_button_borders": ["game/gui.rpy", 188], "gui.check_button_borders": ["game/gui.rpy", 190], "gui.confirm_button_text_xalign": ["game/gui.rpy", 192], "gui.page_button_borders": ["game/gui.rpy", 194], "gui.quick_button_borders": ["game/gui.rpy", 196], "gui.quick_button_text_size": ["game/gui.rpy", 197], "gui.quick_button_text_idle_color": ["game/gui.rpy", 198], "gui.quick_button_text_selected_color": ["game/gui.rpy", 199], "gui.choice_button_width": ["game/gui.rpy", 212], "gui.choice_button_height": ["game/gui.rpy", 213], "gui.choice_button_tile": ["game/gui.rpy", 214], "gui.choice_button_borders": ["game/gui.rpy", 215], "gui.choice_button_text_font": ["game/gui.rpy", 216], "gui.choice_button_text_size": ["game/gui.rpy", 217], "gui.choice_button_text_xalign": ["game/gui.rpy", 218], "gui.choice_button_text_idle_color": ["game/gui.rpy", 219], "gui.choice_button_text_hover_color": ["game/gui.rpy", 220], "gui.choice_button_text_insensitive_color": ["game/gui.rpy", 221], "gui.slot_button_width": ["game/gui.rpy", 231], "gui.slot_button_height": ["game/gui.rpy", 232], "gui.slot_button_borders": ["game/gui.rpy", 233], "gui.slot_button_text_size": ["game/gui.rpy", 234], "gui.slot_button_text_xalign": ["game/gui.rpy", 235], "gui.slot_button_text_idle_color": ["game/gui.rpy", 236], "gui.slot_button_text_selected_idle_color": ["game/gui.rpy", 237], "gui.slot_button_text_selected_hover_color": ["game/gui.rpy", 238], "config.thumbnail_width": ["game/gui.rpy", 241], "config.thumbnail_height": ["game/gui.rpy", 242], "gui.file_slot_cols": ["game/gui.rpy", 245], "gui.file_slot_rows": ["game/gui.rpy", 246], "gui.navigation_xpos": ["game/gui.rpy", 256], "gui.skip_ypos": ["game/gui.rpy", 259], "gui.notify_ypos": ["game/gui.rpy", 262], "gui.choice_spacing": ["game/gui.rpy", 265], "gui.navigation_spacing": ["game/gui.rpy", 268], "gui.pref_spacing": ["game/gui.rpy", 271], "gui.pref_button_spacing": ["game/gui.rpy", 274], "gui.page_spacing": ["game/gui.rpy", 277], "gui.slot_spacing": ["game/gui.rpy", 280], "gui.main_menu_text_xalign": ["game/gui.rpy", 283], "gui.frame_borders": ["game/gui.rpy", 292], "gui.confirm_frame_borders": ["game/gui.rpy", 295], "gui.skip_frame_borders": ["game/gui.rpy", 298], "gui.notify_frame_borders": ["game/gui.rpy", 301], "gui.frame_tile": ["game/gui.rpy", 304], "gui.bar_size": ["game/gui.rpy", 316], "gui.scrollbar_size": ["game/gui.rpy", 317], "gui.slider_size": ["game/gui.rpy", 318], "gui.bar_tile": ["game/gui.rpy", 322], "gui.scrollbar_tile": ["game/gui.rpy", 323], "gui.slider_tile": ["game/gui.rpy", 324], "gui.bar_borders": ["game/gui.rpy", 327], "gui.scrollbar_borders": ["game/gui.rpy", 328], "gui.slider_borders": ["game/gui.rpy", 329], "gui.vbar_borders": ["game/gui.rpy", 332], "gui.vscrollbar_borders": ["game/gui.rpy", 333], "gui.vslider_borders": ["game/gui.rpy", 334], "gui.unscrollable": ["game/gui.rpy", 338], "config.history_length": ["game/gui.rpy", 346], "gui.history_height": ["game/gui.rpy", 350], "gui.history_name_xpos": ["game/gui.rpy", 354], "gui.history_name_ypos": ["game/gui.rpy", 355], "gui.history_name_width": ["game/gui.rpy", 356], "gui.history_name_xalign": ["game/gui.rpy", 357], "gui.history_text_xpos": ["game/gui.rpy", 360], "gui.history_text_ypos": ["game/gui.rpy", 361], "gui.history_text_width": ["game/gui.rpy", 362], "gui.history_text_xalign": ["game/gui.rpy", 363], "gui.nvl_borders": ["game/gui.rpy", 371], "gui.nvl_list_length": ["game/gui.rpy", 375], "gui.nvl_height": ["game/gui.rpy", 379], "gui.nvl_spacing": ["game/gui.rpy", 383], "gui.nvl_name_xpos": ["game/gui.rpy", 387], "gui.nvl_name_ypos": ["game/gui.rpy", 388], "gui.nvl_name_width": ["game/gui.rpy", 389], "gui.nvl_name_xalign": ["game/gui.rpy", 390], "gui.nvl_text_xpos": ["game/gui.rpy", 393], "gui.nvl_text_ypos": ["game/gui.rpy", 394], "gui.nvl_text_width": ["game/gui.rpy", 395], "gui.nvl_text_xalign": ["game/gui.rpy", 396], "gui.nvl_thought_xpos": ["game/gui.rpy", 400], "gui.nvl_thought_ypos": ["game/gui.rpy", 401], "gui.nvl_thought_width": ["game/gui.rpy", 402], "gui.nvl_thought_xalign": ["game/gui.rpy", 403], "gui.nvl_button_xpos": ["game/gui.rpy", 406], "gui.nvl_button_xalign": ["game/gui.rpy", 407], "gui.language": ["game/gui.rpy", 416], "quick_menu": ["game/screens.rpy", 267], "gui.history_allow_tags": ["game/screens.rpy", 1031], "config.nvl_list_length": ["game/screens.rpy", 1457], "bubble.frame": ["game/screens.rpy", 1566], "bubble.thoughtframe": ["game/screens.rpy", 1567], "bubble.properties": ["game/screens.rpy", 1569], "bubble.expand_area": ["game/screens.rpy", 1595], "sprite_focus": ["game/00auto-highlight.rpy", 72], "speaking_char": ["game/00auto-highlight.rpy", 79], "mousetooltip": ["game/01_init.rpy", 112], "monsters": ["game/dialogs/battle.rpy", 1], "magic": ["game/dialogs/battle.rpy", 20], "weapons": ["game/dialogs/battle.rpy", 34], "m": ["game/init.rpy", 2], "s": ["game/init.rpy", 3], "d": ["game/init.rpy", 4], "k": ["game/init.rpy", 5], "u": ["game/init.rpy", 6], "x": ["game/init.rpy", 7], "t": ["game/init.rpy", 8], "z": ["game/init.rpy", 9], "l": ["game/init.rpy", 10], "b": ["game/init.rpy", 11], "config.main_menu_music": ["game/init.rpy", 178], "config.name": ["game/options.rpy", 15], "gui.show_name": ["game/options.rpy", 21], "config.version": ["game/options.rpy", 26], "gui.about": ["game/options.rpy", 32], "build.name": ["game/options.rpy", 40], "config.has_sound": ["game/options.rpy", 49], "config.has_music": ["game/options.rpy", 50], "config.has_voice": ["game/options.rpy", 51], "config.enter_transition": ["game/options.rpy", 76], "config.exit_transition": ["game/options.rpy", 77], "config.intra_transition": ["game/options.rpy", 82], "config.after_load_transition": ["game/options.rpy", 87], "config.end_game_transition": ["game/options.rpy", 92], "config.window": ["game/options.rpy", 109], "config.window_show_transition": ["game/options.rpy", 114], "config.window_hide_transition": ["game/options.rpy", 115], "config.save_directory": ["game/options.rpy", 147], "config.window_icon": ["game/options.rpy", 154], "audio.block": ["game/scripts/define/assets/audio.rpy", 1], "audio.fanfare": ["game/scripts/define/assets/audio.rpy", 2], "sfx_whoosh": ["game/scripts/define/assets/audio.rpy", 3], "sfx_monsterdead": ["game/scripts/define/assets/audio.rpy", 4], "move_time": ["game/scripts/define/assets/transforms.rpy", 1], "stand_anchor": ["game/scripts/define/assets/transforms.rpy", 2], "move_size": ["game/scripts/define/assets/transforms.rpy", 3], "fixedset": ["game/scripts/define/battle_def.rpy", 270], "tt_timer": ["game/scripts/define/battle_def.rpy", 271], "damage": ["game/scripts/define/battle_def.rpy", 272], "m_damage": ["game/scripts/define/battle_def.rpy", 273], "dropitem": ["game/scripts/define/battle_def.rpy", 274], "atk_sfx": ["game/scripts/define/battle_def.rpy", 275], "mp_lost": ["game/scripts/define/battle_def.rpy", 276], "hp_lost": ["game/scripts/define/battle_def.rpy", 277], "players": ["game/scripts/define/battle_def.rpy", 278], "monsters_total": ["game/scripts/define/battle_def.rpy", 279], "monsters_dead": ["game/scripts/define/battle_def.rpy", 280], "b_skill": ["game/scripts/define/battle_def.rpy", 282], "message": ["game/scripts/define/battle_def.rpy", 283], "target": ["game/scripts/define/battle_def.rpy", 284], "picked_targs": ["game/scripts/define/battle_def.rpy", 286], "party_list": ["game/scripts/define/battle_def.rpy", 287], "wild_monsters": ["game/scripts/define/battle_def.rpy", 288], "battle_players": ["game/scripts/define/battle_def.rpy", 289], "alive_players": ["game/scripts/define/battle_def.rpy", 290], "battle_monsters": ["game/scripts/define/battle_def.rpy", 291], "misstext_list": ["game/scripts/define/battle_def.rpy", 292], "diss": ["game/scripts/define/battle_def.rpy", 294], "doubleattack": ["game/scripts/define/battle_def.rpy", 299], "attackall": ["game/scripts/define/battle_def.rpy", 300], "giftofangels": ["game/scripts/define/battle_def.rpy", 301], "loved": ["game/scripts/define/battle_def.rpy", 302], "souldrain": ["game/scripts/define/battle_def.rpy", 303], "souldrain2": ["game/scripts/define/battle_def.rpy", 304], "mindfreeze": ["game/scripts/define/battle_def.rpy", 307], "mindfire": ["game/scripts/define/battle_def.rpy", 308], "magicheal": ["game/scripts/define/battle_def.rpy", 309], "defenseup": ["game/scripts/define/battle_def.rpy", 310], "arrowhail": ["game/scripts/define/battle_def.rpy", 311], "lavaburst": ["game/scripts/define/battle_def.rpy", 312], "swordofdeath": ["game/scripts/define/battle_def.rpy", 313], "spikeshield": ["game/scripts/define/battle_def.rpy", 314], "magicswap": ["game/scripts/define/battle_def.rpy", 315], "lovedefence": ["game/scripts/define/battle_def.rpy", 316], "meteorshower": ["game/scripts/define/battle_def.rpy", 319], "hellrage": ["game/scripts/define/battle_def.rpy", 320], "lifedrain": ["game/scripts/define/battle_def.rpy", 321], "devastationbeam": ["game/scripts/define/battle_def.rpy", 322], "energybeams": ["game/scripts/define/battle_def.rpy", 323], "thunderbolt": ["game/scripts/define/battle_def.rpy", 325], "asteroid": ["game/scripts/define/battle_def.rpy", 326], "rockthrow": ["game/scripts/define/battle_def.rpy", 327], "circleofhealing": ["game/scripts/define/battle_def.rpy", 328], "mindburn": ["game/scripts/define/battle_def.rpy", 329], "mindblast": ["game/scripts/define/battle_def.rpy", 330], "deathmissile": ["game/scripts/define/battle_def.rpy", 331], "magics": ["game/scripts/define/battle_def.rpy", 333], "radar": ["game/scripts/define/battle_def.rpy", 371], "passive1": ["game/scripts/define/battle_def.rpy", 372], "passive2": ["game/scripts/define/battle_def.rpy", 373], "character.p1": ["game/scripts/define/char_def.rpy", 88], "p1": ["game/scripts/define/char_def.rpy", 89], "character.p2": ["game/scripts/define/char_def.rpy", 90], "p2": ["game/scripts/define/char_def.rpy", 91], "character.a": ["game/scripts/define/char_def.rpy", 93], "a": ["game/scripts/define/char_def.rpy", 94], "character.sasha": ["game/scripts/define/char_def.rpy", 96], "sasha": ["game/scripts/define/char_def.rpy", 97], "character.boris": ["game/scripts/define/char_def.rpy", 99], "boris": ["game/scripts/define/char_def.rpy", 100], "character.maks": ["game/scripts/define/char_def.rpy", 102], "maks": ["game/scripts/define/char_def.rpy", 103], "character.lox": ["game/scripts/define/char_def.rpy", 105], "lox": ["game/scripts/define/char_def.rpy", 106], "character.sanek": ["game/scripts/define/char_def.rpy", 108], "sanek": ["game/scripts/define/char_def.rpy", 109], "character.tanka": ["game/scripts/define/char_def.rpy", 111], "tanka": ["game/scripts/define/char_def.rpy", 112], "character.maksim": ["game/scripts/define/char_def.rpy", 114], "maksim": ["game/scripts/define/char_def.rpy", 115], "cookbook": ["game/scripts/define/items_def.rpy", 1], "inv": ["game/scripts/define/items_def.rpy", 2], "name": ["game/scripts/other/setup.rpy", 1], "currentplayer": ["game/scripts/other/setup.rpy", 2], "eventrunning": ["game/scripts/other/setup.rpy", 3]}, "screen": {"say": ["game/screens.rpy", 97], "input": ["game/screens.rpy", 175], "choice": ["game/screens.rpy", 208], "quick_menu": ["game/screens.rpy", 1616], "navigation": ["game/screens.rpy", 288], "main_menu": ["game/screens.rpy", 357], "game_menu": ["game/screens.rpy", 421], "about": ["game/screens.rpy", 547], "save": ["game/screens.rpy", 585], "load": ["game/screens.rpy", 592], "file_slots": ["game/screens.rpy", 599], "preferences": ["game/screens.rpy", 727], "history": ["game/screens.rpy", 989], "help": ["game/screens.rpy", 1079], "keyboard_help": ["game/screens.rpy", 1108], "mouse_help": ["game/screens.rpy", 1159], "gamepad_help": ["game/screens.rpy", 1182], "confirm": ["game/screens.rpy", 1248], "skip_indicator": ["game/screens.rpy", 1311], "notify": ["game/screens.rpy", 1366], "nvl": ["game/screens.rpy", 1405], "nvl_dialogue": ["game/screens.rpy", 1437], "bubble": ["game/screens.rpy", 1524], "world_time": ["game/dialogs/map.rpy", 1], "map": ["game/dialogs/map.rpy", 16], "select_p1": ["game/scripts/battle/battle.rpy", 87], "select_p2": ["game/scripts/battle/battle.rpy", 98], "battle_tooltip": ["game/scripts/battle/battle.rpy", 109], "battle_overlay": ["game/scripts/battle/battle.rpy", 121], "display_monsters": ["game/scripts/battle/battle.rpy", 149], "battle_message": ["game/scripts/battle/battle.rpy", 181], "turn_select": ["game/scripts/battle/player_actions.rpy", 18], "choose_skill": ["game/scripts/battle/player_actions.rpy", 50], "select_ally": ["game/scripts/battle/player_actions.rpy", 115], "select_monster": ["game/scripts/battle/player_actions.rpy", 132], "monster_dmg": ["game/scripts/battle/player_actions.rpy", 139], "player_dmg": ["game/scripts/battle/player_actions.rpy", 150], "inventory_inbattle": ["game/scripts/define/items_def.rpy", 97], "inventory_battleview": ["game/scripts/define/items_def.rpy", 113], "by_item": ["game/scripts/other/inventory.rpy", 167], "shop_menu": ["game/scripts/other/inventory.rpy", 186], "magic_shop_menu": ["game/scripts/other/inventory.rpy", 237], "by_magic": ["game/scripts/other/inventory.rpy", 261], "EquipmentScreen": ["game/scripts/other/inventory.rpy", 278], "inv_tooltip": ["game/scripts/other/inventory.rpy", 354], "inventory_screen": ["game/scripts/other/inventory.rpy", 364], "inventory_view": ["game/scripts/other/inventory.rpy", 393], "money": ["game/scripts/other/inventory.rpy", 444], "banking": ["game/scripts/other/inventory.rpy", 452], "crafting": ["game/scripts/other/inventory.rpy", 470], "view_nav": ["game/scripts/other/inventory.rpy", 506], "sort_nav": ["game/scripts/other/inventory.rpy", 513], "inventory_popup": ["game/scripts/other/inventory.rpy", 525]}, "transform": {"delayed_blink": ["game/screens.rpy", 1329], "notify_appear": ["game/screens.rpy", 1377], "sprite_highlight": ["game/00auto-highlight.rpy", 87], "idle_x": ["game/scripts/define/assets/transforms.rpy", 5], "idle_y": ["game/scripts/define/assets/transforms.rpy", 11], "idle_xy": ["game/scripts/define/assets/transforms.rpy", 16], "idle_shake": ["game/scripts/define/assets/transforms.rpy", 30], "idle_sway": ["game/scripts/define/assets/transforms.rpy", 37], "slow_sway": ["game/scripts/define/assets/transforms.rpy", 44], "squeeze": ["game/scripts/define/assets/transforms.rpy", 51], "char_sway": ["game/scripts/define/assets/transforms.rpy", 68], "shaking": ["game/scripts/define/assets/transforms.rpy", 73], "shake_fade": ["game/scripts/define/assets/transforms.rpy", 78]}, "callable": {"parse_random": ["game/01_init.rpy", 16], "next_random": ["game/01_init.rpy", 43], "name_callback": ["game/00auto-highlight.rpy", 95], "SpriteFocus.__init__": ["game/00auto-highlight.rpy", 105], "SpriteFocus.__call__": ["game/00auto-highlight.rpy", 112], "RandomBag.__init__": ["game/01_init.rpy", 4], "RandomBag.draw": ["game/01_init.rpy", 8], "touch": ["game/gui.rpy", 428], "small": ["game/gui.rpy", 435], "MouseTooltip.__init__": ["game/01_init.rpy", 65], "MouseTooltip.render": ["game/01_init.rpy", 76], "MouseTooltip.event": ["game/01_init.rpy", 97], "TransitionConditionSwitch.__init__": ["game/01_init.rpy", 116], "TransitionConditionSwitch.render": ["game/01_init.rpy", 126], "TransitionConditionSwitch.per_interact": ["game/01_init.rpy", 140], "TransitionConditionSwitch.visit": ["game/01_init.rpy", 163], "ending": ["game/init.rpy", 151], "OneDiscordMessage": ["game/init.rpy", 157], "DiscordMessage": ["game/init.rpy", 162], "addTime": ["game/init.rpy", 165], "random_choise": ["game/init.rpy", 170], "DispTextStyle.__init__": ["game/kinetic_text_tags.rpy", 63], "DispTextStyle.add_tags": ["game/kinetic_text_tags.rpy", 67], "DispTextStyle.apply_style": ["game/kinetic_text_tags.rpy", 84], "DispTextStyle.start_tags": ["game/kinetic_text_tags.rpy", 95], "DispTextStyle.end_tags": ["game/kinetic_text_tags.rpy", 114], "BounceText.__init__": ["game/kinetic_text_tags.rpy", 130], "BounceText.render": ["game/kinetic_text_tags.rpy", 145], "BounceText.event": ["game/kinetic_text_tags.rpy", 167], "BounceText.visit": ["game/kinetic_text_tags.rpy", 170], "FadeInText.__init__": ["game/kinetic_text_tags.rpy", 177], "FadeInText.render": ["game/kinetic_text_tags.rpy", 192], "FadeInText.visit": ["game/kinetic_text_tags.rpy", 211], "ScareText.__init__": ["game/kinetic_text_tags.rpy", 216], "ScareText.render": ["game/kinetic_text_tags.rpy", 224], "ScareText.visit": ["game/kinetic_text_tags.rpy", 237], "ChaosText.__init__": ["game/kinetic_text_tags.rpy", 252], "ChaosText.render": ["game/kinetic_text_tags.rpy", 261], "ChaosText.visit": ["game/kinetic_text_tags.rpy", 298], "RotateText.__init__": ["game/kinetic_text_tags.rpy", 303], "RotateText.render": ["game/kinetic_text_tags.rpy", 310], "RotateText.visit": ["game/kinetic_text_tags.rpy", 326], "SwapText.__init__": ["game/kinetic_text_tags.rpy", 388], "SwapText.render": ["game/kinetic_text_tags.rpy", 405], "SwapText.visit": ["game/kinetic_text_tags.rpy", 428], "MoveText.__init__": ["game/kinetic_text_tags.rpy", 437], "MoveText.render": ["game/kinetic_text_tags.rpy", 444], "MoveText.event": ["game/kinetic_text_tags.rpy", 466], "MoveText.visit": ["game/kinetic_text_tags.rpy", 471], "bounce_tag": ["game/kinetic_text_tags.rpy", 486], "fade_in_tag": ["game/kinetic_text_tags.rpy", 540], "scare_tag": ["game/kinetic_text_tags.rpy", 579], "chaos_tag": ["game/kinetic_text_tags.rpy", 607], "rotate_tag": ["game/kinetic_text_tags.rpy", 626], "swap_tag": ["game/kinetic_text_tags.rpy", 661], "move_tag": ["game/kinetic_text_tags.rpy", 687], "paragraph_tag": ["game/kinetic_text_tags.rpy", 714], "omega_tag": ["game/kinetic_text_tags.rpy", 736], "monstersFixed": ["game/scripts/define/battle_def.rpy", 2], "monstersRoll": ["game/scripts/define/battle_def.rpy", 54], "asignPos": ["game/scripts/define/battle_def.rpy", 84], "swapSlot": ["game/scripts/define/battle_def.rpy", 102], "partyRevive": ["game/scripts/define/battle_def.rpy", 108], "restorehp": ["game/scripts/define/battle_def.rpy", 114], "restoremp": ["game/scripts/define/battle_def.rpy", 119], "startPlayersTurn": ["game/scripts/define/battle_def.rpy", 124], "endTurn": ["game/scripts/define/battle_def.rpy", 129], "startTurn": ["game/scripts/define/battle_def.rpy", 166], "playersCnt": ["game/scripts/define/battle_def.rpy", 196], "playersChk": ["game/scripts/define/battle_def.rpy", 207], "getImage": ["game/scripts/define/battle_def.rpy", 238], "playerAction": ["game/scripts/define/battle_def.rpy", 244], "runEvent": ["game/scripts/define/battle_def.rpy", 253], "stopEvent": ["game/scripts/define/battle_def.rpy", 261], "atkAll": ["game/scripts/define/battle_formulas.rpy", 2], "atkRow": ["game/scripts/define/battle_formulas.rpy", 14], "atkEnemy": ["game/scripts/define/battle_formulas.rpy", 25], "atkAlly": ["game/scripts/define/battle_formulas.rpy", 37], "atkSelf": ["game/scripts/define/battle_formulas.rpy", 45], "Defend": ["game/scripts/define/battle_formulas.rpy", 52], "accFormula": ["game/scripts/define/battle_formulas.rpy", 85], "dmgFormula": ["game/scripts/define/battle_formulas.rpy", 79], "Attack": ["game/scripts/define/battle_formulas.rpy", 109], "expFormula": ["game/scripts/define/battle_formulas.rpy", 129], "monsterTurns": ["game/scripts/define/battle_monsters.rpy", 2], "monsterTarg": ["game/scripts/define/battle_monsters.rpy", 39], "monsterAtk": ["game/scripts/define/battle_monsters.rpy", 65], "monsterDmg": ["game/scripts/define/battle_monsters.rpy", 80], "monsterImg": ["game/scripts/define/battle_monsters.rpy", 96], "Char.__init__": ["game/scripts/define/char_def.rpy", 4], "Char.addSkill": ["game/scripts/define/char_def.rpy", 46], "Char.addEquip": ["game/scripts/define/char_def.rpy", 49], "Char.removeEquip": ["game/scripts/define/char_def.rpy", 76], "getTarget": ["game/scripts/define/items_def.rpy", 53], "itemUsable": ["game/scripts/define/items_def.rpy", 59], "useItem": ["game/scripts/define/items_def.rpy", 72], "Monster.__init__": ["game/scripts/define/monsters_def.rpy", 47], "canTarget": ["game/scripts/define/skill_def.rpy", 13], "skillChk": ["game/scripts/define/skill_def.rpy", 33], "afterFX": ["game/scripts/define/skill_def.rpy", 41], "radarFX": ["game/scripts/define/skill_def.rpy", 54], "sensIf": ["game/scripts/define/skill_def.rpy", 71], "Skill.__init__": ["game/scripts/define/skill_def.rpy", 81], "Skill.addSkill": ["game/scripts/define/skill_def.rpy", 89], "Skill.useSkill": ["game/scripts/define/skill_def.rpy", 95], "PassiveSkill.__init__": ["game/scripts/define/skill_def.rpy", 120], "ActiveSkill.__init__": ["game/scripts/define/skill_def.rpy", 130], "Item.__init__": ["game/scripts/other/inventory.rpy", 6], "Item.change": ["game/scripts/other/inventory.rpy", 22], "Armor.__init__": ["game/scripts/other/inventory.rpy", 36], "Weapon.__init__": ["game/scripts/other/inventory.rpy", 44], "Accessory.__init__": ["game/scripts/other/inventory.rpy", 52], "Inventory.__init__": ["game/scripts/other/inventory.rpy", 61], "Inventory.buy": ["game/scripts/other/inventory.rpy", 70], "Inventory.check": ["game/scripts/other/inventory.rpy", 75], "Inventory.check_recipe": ["game/scripts/other/inventory.rpy", 81], "Inventory.craft": ["game/scripts/other/inventory.rpy", 91], "Inventory.deposit": ["game/scripts/other/inventory.rpy", 98], "Inventory.drop": ["game/scripts/other/inventory.rpy", 101], "Inventory.qty": ["game/scripts/other/inventory.rpy", 109], "Inventory.sell": ["game/scripts/other/inventory.rpy", 114], "Inventory.sort_name": ["game/scripts/other/inventory.rpy", 118], "Inventory.sort_qty": ["game/scripts/other/inventory.rpy", 121], "Inventory.sort_value": ["game/scripts/other/inventory.rpy", 124], "Inventory.take": ["game/scripts/other/inventory.rpy", 127], "Inventory.withdraw": ["game/scripts/other/inventory.rpy", 134], "calculate_price": ["game/scripts/other/inventory.rpy", 137], "money_transfer": ["game/scripts/other/inventory.rpy", 142], "trade": ["game/scripts/other/inventory.rpy", 150], "transaction": ["game/scripts/other/inventory.rpy", 154], "consume": ["game/scripts/other/inventory.rpy", 162]}}, "build": {"directory_name": "Denisinshcool-1.6", "executable_name": "Denisinshcool", "include_update": false, "packages": [{"name": "gameonly", "formats": ["null"], "file_lists": ["all"], "description": "Game-Only Update for Mobile", "update": true, "dlc": false, "hidden": true}, {"name": "pc", "formats": ["zip"], "file_lists": ["windows", "linux", "renpy", "all"], "description": "PC: Windows and Linux", "update": true, "dlc": false, "hidden": false}, {"name": "linux", "formats": ["tar.bz2"], "file_lists": ["linux", "linux_arm", "renpy", "all"], "description": "Linux", "update": true, "dlc": false, "hidden": false}, {"name": "mac", "formats": ["app-zip", "app-dmg"], "file_lists": ["mac", "renpy", "all"], "description": "Macintosh", "update": true, "dlc": false, "hidden": false}, {"name": "win", "formats": ["zip"], "file_lists": ["windows", "renpy", "all"], "description": "Windows", "update": true, "dlc": false, "hidden": false}, {"name": "market", "formats": ["bare-zip"], "file_lists": ["windows", "linux", "mac", "renpy", "all"], "description": "Windows, Mac, Linux for Markets", "update": true, "dlc": false, "hidden": false}, {"name": "steam", "formats": ["zip"], "file_lists": ["windows", "linux", "mac", "renpy", "all"], "description": "steam", "update": true, "dlc": false, "hidden": true}, {"name": "android", "formats": ["directory"], "file_lists": ["android", "all"], "description": "android", "update": false, "dlc": true, "hidden": true}, {"name": "ios", "formats": ["directory"], "file_lists": ["ios", "all"], "description": "ios", "update": false, "dlc": true, "hidden": true}, {"name": "web", "formats": ["zip"], "file_lists": ["web", "renpy", "all"], "description": "web", "update": false, "dlc": true, "hidden": true}], "archives": [["archive", ["all"]]], "documentation_patterns": ["*.html", "*.txt"], "base_patterns": [["*.py", null], ["*.sh", null], ["*.app/", null], ["*.dll", null], ["*.manifest", null], ["*.keystore", null], ["update.pem", null], ["lib/", null], ["renpy/", null], ["update/", null], ["common/", null], ["update/", null], ["old-game/", null], ["base/", null], ["icon.ico", null], ["icon.icns", null], ["project.json", null], ["log.txt", null], ["errors.txt", null], ["traceback.txt", null], ["image_cache.txt", null], ["text_overflow.txt", null], ["dialogue.txt", null], ["dialogue.tab", null], ["profile_screen.txt", null], ["files.txt", null], ["memory.txt", null], ["tmp/", null], ["game/saves/", null], ["game/bytecode.rpyb", null], ["archived/", null], ["launcherinfo.py", null], ["android.txt", null], ["game/presplash*.*", ["all"]], ["android.json", ["android"]], [".android.json", ["android"]], ["android-*.png", ["android"]], ["android-*.jpg", ["android"]], ["ouya_icon.png", null], ["ios-presplash.*", ["ios"]], ["ios-launchimage.png", null], ["ios-icon.png", null], ["web-presplash.png", ["web"]], ["web-presplash.jpg", ["web"]], ["web-presplash.webp", ["web"]], ["web-icon.png", ["web"]], ["progressive_download.txt", ["web"]], ["steam_appid.txt", null], ["game/cache/bytecode-39.rpyb", ["all"]], ["game/cache/bytecode-311.rpyb", ["web"]], ["game/cache/bytecode-*.rpyb", null], ["game/cache/build_info.json", null], ["game/cache/build_time.txt", null], ["**~", null], ["**.bak", null], ["**/.**", null], ["**/#**", null], ["**/thumbs.db", null], [".*", null], ["**", ["all"]]], "renpy_patterns": [["renpy/common/_compat/**", null], ["renpy/common/_roundrect/**", null], ["renpy/common/_outline/**", null], ["renpy/common/_theme**", null], ["renpy/**__pycache__/**.cpython-39.pyc", ["all"]], ["renpy/**__pycache__", ["all"]], ["**~", null], ["**/#*", null], ["**/.*", null], ["**.old", null], ["**.new", null], ["**.rpa", null], ["**/steam_appid.txt", null], ["renpy.py", ["all"]], ["renpy/", ["all"]], ["renpy/**.py", ["renpy"]], ["renpy/**.pxd", null], ["renpy/**.pxi", null], ["renpy/**.pyx", null], ["renpy/**.pyc", null], ["renpy/**.pyo", null], ["renpy/common/", ["all"]], ["renpy/common/_compat/**", ["renpy"]], ["renpy/common/**.rpy", ["renpy"]], ["renpy/common/**.rpym", ["renpy"]], ["renpy/common/_compat/**", ["renpy"]], ["renpy/common/**", ["all"]], ["renpy/**", ["all"]], ["lib/*/renpy", null], ["lib/*/renpy.exe", null], ["lib/*/pythonw.exe", null], ["lib/py2-*/", null], ["lib/py*-windows-i686/**", ["windows_i686"]], ["lib/py*-windows-x86_64/**", ["windows"]], ["lib/py*-linux-i686/**", ["linux_i686"]], ["lib/py*-linux-aarch64/**", ["linux_arm"]], ["lib/py*-linux-armv7l/**", ["linux_arm"]], ["lib/py*-linux-*/**", ["linux"]], ["lib/py*-mac-*/**", ["mac"]], ["lib/python2.*/**", null], ["lib/**", ["windows", "linux", "mac", "android", "ios"]], ["renpy.sh", ["linux", "mac"]]], "xbit_patterns": ["**.sh", "lib/py*-linux-*/*", "lib/py*-mac-*/*", "**.app/Contents/MacOS/*"], "version": "1.6", "display_name": "Denis in shcool", "exclude_empty_directories": true, "allow_integrated_gpu": true, "renpy": false, "script_version": true, "destination": "Denisinshcool-1.6-dists", "itch_channels": {"*-all.zip": "win-osx-linux", "*-market.zip": "win-osx-linux", "*-pc.zip": "win-linux", "*-win.zip": "win", "*-mac.zip": "osx", "*-linux.tar.bz2": "linux", "*-release.apk": "android"}, "mac_info_plist": {}, "merge": [["linux_i686", "linux"], ["windows_i686", "windows"]], "include_i686": true, "change_icon_i686": true, "android_permissions": [], "_sdk_fonts": false, "update_formats": ["rpu"], "info": {"info": {}, "time": 1713629982.8894203, "name": "Denis in shcool", "version": "1.6"}}}